{"duration": 158.425555229187, "input_args": {"imgs": "<nibabel.nifti1.Nifti1Image object at 0x7f7f6eb66250>", "extraction_function": "<nilearn.maskers.nifti_spheres_masker._ExtractionFunctor object at 0x7f7f71987d00>", "parameters": "{'allow_overlap': False, 'detrend': False, 'dtype': None, 'high_pass': None, 'high_variance_confounds': False, 'low_pass': None, 'mask_img': None, 'radius': 6, 'seeds': [(-24.282068338245157, -52.0502670481801, 33.4499782808125)], 'smoothing_fwhm': None, 'standardize': False, 'standardize_confounds': True, 't_r': None}", "confounds": "None", "sample_mask": "None", "copy": "True", "dtype": "None"}}